{
  "report_date": "2026-05-10",
  "exchange": "okx",
  "generated_at": "2026-05-11T14:43:11+08:00",
  "symbol_count": 100,
  "with_hits_count": 1,
  "rows": [
    {
      "rank_vol": 1,
      "symbol": "XPD/USDT",
      "quote_volume": 0.0,
      "total_klines": 288,
      "hit_count": 0,
      "max_amplitude": 0.4717,
      "hits": [],
      "error": null
    },
    {
      "rank_vol": 2,
      "symbol": "WIF/USDT",
      "quote_volume": 0.0,
      "total_klines": 288,
      "hit_count": 0,
      "max_amplitude": 0.7535,
      "hits": [],
      "error": null
    },
    {
      "rank_vol": 3,
      "symbol": "PI/USDT",
      "quote_volume": 0.0,
      "total_klines": 288,
      "hit_count": 0,
      "max_amplitude": 0.9765,
      "hits": [],
      "error": null
    },
    {
      "rank_vol": 4,
      "symbol": "EDGE/USDT",
      "quote_volume": 0.0,
      "total_klines": 288,
      "hit_count": 0,
      "max_amplitude": 1.5027,
      "hits": [],
      "error": null
    },
    {
      "rank_vol": 5,
      "symbol": "RECALL/USDT",
      "quote_volume": 0.0,
      "total_klines": 288,
      "hit_count": 0,
      "max_amplitude": 3.2539,
      "hits": [],
      "error": null
    },
    {
      "rank_vol": 6,
      "symbol": "SUSHI/USDT",
      "quote_volume": 0.0,
      "total_klines": 288,
      "hit_count": 0,
      "max_amplitude": 1.3748,
      "hits": [],
      "error": null
    },
    {
      "rank_vol": 7,
      "symbol": "RAVE/USDT",
      "quote_volume": 0.0,
      "total_klines": 288,
      "hit_count": 0,
      "max_amplitude": 10.014,
      "hits": [],
      "error": null
    },
    {
      "rank_vol": 8,
      "symbol": "XLM/USDT",
      "quote_volume": 0.0,
      "total_klines": 288,
      "hit_count": 0,
      "max_amplitude": 0.6031,
      "hits": [],
      "error": null
    },
    {
      "rank_vol": 9,
      "symbol": "DASH/USDT",
      "quote_volume": 0.0,
      "total_klines": 288,
      "hit_count": 0,
      "max_amplitude": 1.2643,
      "hits": [],
      "error": null
    },
    {
      "rank_vol": 10,
      "symbol": "TRUST/USDT",
      "quote_volume": 0.0,
      "total_klines": 288,
      "hit_count": 0,
      "max_amplitude": 2.9392,
      "hits": [],
      "error": null
    },
    {
      "rank_vol": 11,
      "symbol": "GPS/USDT",
      "quote_volume": 0.0,
      "total_klines": 288,
      "hit_count": 0,
      "max_amplitude": 1.4685,
      "hits": [],
      "error": null
    },
    {
      "rank_vol": 12,
      "symbol": "CRO/USDT",
      "quote_volume": 0.0,
      "total_klines": 288,
      "hit_count": 0,
      "max_amplitude": 0.8743,
      "hits": [],
      "error": null
    },
    {
      "rank_vol": 13,
      "symbol": "ACU/USDT",
      "quote_volume": 0.0,
      "total_klines": 288,
      "hit_count": 0,
      "max_amplitude": 2.4309,
      "hits": [],
      "error": null
    },
    {
      "rank_vol": 14,
      "symbol": "UNI/USDT",
      "quote_volume": 0.0,
      "total_klines": 288,
      "hit_count": 0,
      "max_amplitude": 2.1385,
      "hits": [],
      "error": null
    },
    {
      "rank_vol": 15,
      "symbol": "STRK/USDT",
      "quote_volume": 0.0,
      "total_klines": 288,
      "hit_count": 0,
      "max_amplitude": 1.8644,
      "hits": [],
      "error": null
    },
    {
      "rank_vol": 16,
      "symbol": "NEIRO/USDT",
      "quote_volume": 0.0,
      "total_klines": 288,
      "hit_count": 0,
      "max_amplitude": 0.9066,
      "hits": [],
      "error": null
    },
    {
      "rank_vol": 17,
      "symbol": "ZKP/USDT",
      "quote_volume": 0.0,
      "total_klines": 288,
      "hit_count": 0,
      "max_amplitude": 1.8274,
      "hits": [],
      "error": null
    },
    {
      "rank_vol": 18,
      "symbol": "APE/USDT",
      "quote_volume": 0.0,
      "total_klines": 288,
      "hit_count": 0,
      "max_amplitude": 1.0626,
      "hits": [],
      "error": null
    },
    {
      "rank_vol": 19,
      "symbol": "LITE/USDT",
      "quote_volume": 0.0,
      "total_klines": 288,
      "hit_count": 0,
      "max_amplitude": 2.2147,
      "hits": [],
      "error": null
    },
    {
      "rank_vol": 20,
      "symbol": "MSTR/USDT",
      "quote_volume": 0.0,
      "total_klines": 288,
      "hit_count": 0,
      "max_amplitude": 0.4075,
      "hits": [],
      "error": null
    },
    {
      "rank_vol": 21,
      "symbol": "ENJ/USDT",
      "quote_volume": 0.0,
      "total_klines": 288,
      "hit_count": 0,
      "max_amplitude": 0.6466,
      "hits": [],
      "error": null
    },
    {
      "rank_vol": 22,
      "symbol": "INJ/USDT",
      "quote_volume": 0.0,
      "total_klines": 288,
      "hit_count": 0,
      "max_amplitude": 0.9872,
      "hits": [],
      "error": null
    },
    {
      "rank_vol": 23,
      "symbol": "RAY/USDT",
      "quote_volume": 0.0,
      "total_klines": 288,
      "hit_count": 0,
      "max_amplitude": 0.8494,
      "hits": [],
      "error": null
    },
    {
      "rank_vol": 24,
      "symbol": "OL/USDT",
      "quote_volume": 0.0,
      "total_klines": 288,
      "hit_count": 0,
      "max_amplitude": 1.8026,
      "hits": [],
      "error": null
    },
    {
      "rank_vol": 25,
      "symbol": "H/USDT",
      "quote_volume": 0.0,
      "total_klines": 288,
      "hit_count": 0,
      "max_amplitude": 3.1819,
      "hits": [],
      "error": null
    },
    {
      "rank_vol": 26,
      "symbol": "OKB/USDT",
      "quote_volume": 0.0,
      "total_klines": 288,
      "hit_count": 0,
      "max_amplitude": 0.8396,
      "hits": [],
      "error": null
    },
    {
      "rank_vol": 27,
      "symbol": "APT/USDT",
      "quote_volume": 0.0,
      "total_klines": 288,
      "hit_count": 0,
      "max_amplitude": 0.9751,
      "hits": [],
      "error": null
    },
    {
      "rank_vol": 28,
      "symbol": "WCT/USDT",
      "quote_volume": 0.0,
      "total_klines": 288,
      "hit_count": 0,
      "max_amplitude": 2.2281,
      "hits": [],
      "error": null
    },
    {
      "rank_vol": 29,
      "symbol": "NEO/USDT",
      "quote_volume": 0.0,
      "total_klines": 288,
      "hit_count": 0,
      "max_amplitude": 2.8022,
      "hits": [],
      "error": null
    },
    {
      "rank_vol": 30,
      "symbol": "SNX/USDT",
      "quote_volume": 0.0,
      "total_klines": 288,
      "hit_count": 0,
      "max_amplitude": 1.8868,
      "hits": [],
      "error": null
    },
    {
      "rank_vol": 31,
      "symbol": "LIT/USDT",
      "quote_volume": 0.0,
      "total_klines": 288,
      "hit_count": 0,
      "max_amplitude": 1.3867,
      "hits": [],
      "error": null
    },
    {
      "rank_vol": 32,
      "symbol": "W/USDT",
      "quote_volume": 0.0,
      "total_klines": 288,
      "hit_count": 0,
      "max_amplitude": 2.167,
      "hits": [],
      "error": null
    },
    {
      "rank_vol": 33,
      "symbol": "SYRUP/USDT",
      "quote_volume": 0.0,
      "total_klines": 288,
      "hit_count": 0,
      "max_amplitude": 0.7908,
      "hits": [],
      "error": null
    },
    {
      "rank_vol": 34,
      "symbol": "AVAX/USDT",
      "quote_volume": 0.0,
      "total_klines": 288,
      "hit_count": 0,
      "max_amplitude": 0.7056,
      "hits": [],
      "error": null
    },
    {
      "rank_vol": 35,
      "symbol": "LPT/USDT",
      "quote_volume": 0.0,
      "total_klines": 288,
      "hit_count": 0,
      "max_amplitude": 0.6055,
      "hits": [],
      "error": null
    },
    {
      "rank_vol": 36,
      "symbol": "ACT/USDT",
      "quote_volume": 0.0,
      "total_klines": 288,
      "hit_count": 0,
      "max_amplitude": 1.0699,
      "hits": [],
      "error": null
    },
    {
      "rank_vol": 37,
      "symbol": "FLOKI/USDT",
      "quote_volume": 0.0,
      "total_klines": 288,
      "hit_count": 0,
      "max_amplitude": 1.7099,
      "hits": [],
      "error": null
    },
    {
      "rank_vol": 38,
      "symbol": "MSFT/USDT",
      "quote_volume": 0.0,
      "total_klines": 288,
      "hit_count": 0,
      "max_amplitude": 0.2933,
      "hits": [],
      "error": null
    },
    {
      "rank_vol": 39,
      "symbol": "MEME/USDT",
      "quote_volume": 0.0,
      "total_klines": 288,
      "hit_count": 0,
      "max_amplitude": 0.6621,
      "hits": [],
      "error": null
    },
    {
      "rank_vol": 40,
      "symbol": "DOGE/USDT",
      "quote_volume": 0.0,
      "total_klines": 288,
      "hit_count": 0,
      "max_amplitude": 0.599,
      "hits": [],
      "error": null
    },
    {
      "rank_vol": 41,
      "symbol": "KGEN/USDT",
      "quote_volume": 0.0,
      "total_klines": 288,
      "hit_count": 0,
      "max_amplitude": 2.7187,
      "hits": [],
      "error": null
    },
    {
      "rank_vol": 42,
      "symbol": "MOODENG/USDT",
      "quote_volume": 0.0,
      "total_klines": 288,
      "hit_count": 0,
      "max_amplitude": 1.1032,
      "hits": [],
      "error": null
    },
    {
      "rank_vol": 43,
      "symbol": "NOT/USDT",
      "quote_volume": 0.0,
      "total_klines": 288,
      "hit_count": 0,
      "max_amplitude": 2.0961,
      "hits": [],
      "error": null
    },
    {
      "rank_vol": 44,
      "symbol": "XCU/USDT",
      "quote_volume": 0.0,
      "total_klines": 288,
      "hit_count": 0,
      "max_amplitude": 2.8984,
      "hits": [],
      "error": null
    },
    {
      "rank_vol": 45,
      "symbol": "AERO/USDT",
      "quote_volume": 0.0,
      "total_klines": 288,
      "hit_count": 0,
      "max_amplitude": 2.1323,
      "hits": [],
      "error": null
    },
    {
      "rank_vol": 46,
      "symbol": "STX/USDT",
      "quote_volume": 0.0,
      "total_klines": 288,
      "hit_count": 0,
      "max_amplitude": 0.641,
      "hits": [],
      "error": null
    },
    {
      "rank_vol": 47,
      "symbol": "GIGGLE/USDT",
      "quote_volume": 0.0,
      "total_klines": 288,
      "hit_count": 0,
      "max_amplitude": 2.8025,
      "hits": [],
      "error": null
    },
    {
      "rank_vol": 48,
      "symbol": "AUCTION/USDT",
      "quote_volume": 0.0,
      "total_klines": 288,
      "hit_count": 0,
      "max_amplitude": 1.9001,
      "hits": [],
      "error": null
    },
    {
      "rank_vol": 49,
      "symbol": "WAL/USDT",
      "quote_volume": 0.0,
      "total_klines": 288,
      "hit_count": 0,
      "max_amplitude": 13.1268,
      "hits": [],
      "error": null
    },
    {
      "rank_vol": 50,
      "symbol": "ETH/USDT",
      "quote_volume": 0.0,
      "total_klines": 288,
      "hit_count": 0,
      "max_amplitude": 0.5007,
      "hits": [],
      "error": null
    },
    {
      "rank_vol": 51,
      "symbol": "SHIB/USDT",
      "quote_volume": 0.0,
      "total_klines": 288,
      "hit_count": 0,
      "max_amplitude": 0.6894,
      "hits": [],
      "error": null
    },
    {
      "rank_vol": 52,
      "symbol": "ZRO/USDT",
      "quote_volume": 0.0,
      "total_klines": 288,
      "hit_count": 0,
      "max_amplitude": 0.8772,
      "hits": [],
      "error": null
    },
    {
      "rank_vol": 53,
      "symbol": "GMX/USDT",
      "quote_volume": 0.0,
      "total_klines": 288,
      "hit_count": 0,
      "max_amplitude": 1.2001,
      "hits": [],
      "error": null
    },
    {
      "rank_vol": 54,
      "symbol": "LAYER/USDT",
      "quote_volume": 0.0,
      "total_klines": 288,
      "hit_count": 1,
      "max_amplitude": 13.1329,
      "hits": [
        {
          "timestamp": "2026-05-10 00:10:00",
          "direction": "下插针 🔻",
          "amplitude": 3.04
        }
      ],
      "error": null
    },
    {
      "rank_vol": 55,
      "symbol": "ARB/USDT",
      "quote_volume": 0.0,
      "total_klines": 288,
      "hit_count": 0,
      "max_amplitude": 1.171,
      "hits": [],
      "error": null
    },
    {
      "rank_vol": 56,
      "symbol": "MINA/USDT",
      "quote_volume": 0.0,
      "total_klines": 288,
      "hit_count": 0,
      "max_amplitude": 0.7247,
      "hits": [],
      "error": null
    },
    {
      "rank_vol": 57,
      "symbol": "IMX/USDT",
      "quote_volume": 0.0,
      "total_klines": 288,
      "hit_count": 0,
      "max_amplitude": 0.7563,
      "hits": [],
      "error": null
    },
    {
      "rank_vol": 58,
      "symbol": "LINEA/USDT",
      "quote_volume": 0.0,
      "total_klines": 288,
      "hit_count": 0,
      "max_amplitude": 1.4008,
      "hits": [],
      "error": null
    },
    {
      "rank_vol": 59,
      "symbol": "PUMP/USDT",
      "quote_volume": 0.0,
      "total_klines": 288,
      "hit_count": 0,
      "max_amplitude": 1.1201,
      "hits": [],
      "error": null
    },
    {
      "rank_vol": 60,
      "symbol": "VANA/USDT",
      "quote_volume": 0.0,
      "total_klines": 288,
      "hit_count": 0,
      "max_amplitude": 1.6422,
      "hits": [],
      "error": null
    },
    {
      "rank_vol": 61,
      "symbol": "FOGO/USDT",
      "quote_volume": 0.0,
      "total_klines": 288,
      "hit_count": 0,
      "max_amplitude": 1.8279,
      "hits": [],
      "error": null
    },
    {
      "rank_vol": 62,
      "symbol": "BASED/USDT",
      "quote_volume": 0.0,
      "total_klines": 288,
      "hit_count": 0,
      "max_amplitude": 5.1535,
      "hits": [],
      "error": null
    },
    {
      "rank_vol": 63,
      "symbol": "ZBT/USDT",
      "quote_volume": 0.0,
      "total_klines": 288,
      "hit_count": 0,
      "max_amplitude": 1.4563,
      "hits": [],
      "error": null
    },
    {
      "rank_vol": 64,
      "symbol": "KITE/USDT",
      "quote_volume": 0.0,
      "total_klines": 288,
      "hit_count": 0,
      "max_amplitude": 4.3526,
      "hits": [],
      "error": null
    },
    {
      "rank_vol": 65,
      "symbol": "XTZ/USDT",
      "quote_volume": 0.0,
      "total_klines": 288,
      "hit_count": 0,
      "max_amplitude": 0.4884,
      "hits": [],
      "error": null
    },
    {
      "rank_vol": 66,
      "symbol": "SUI/USDT",
      "quote_volume": 0.0,
      "total_klines": 288,
      "hit_count": 0,
      "max_amplitude": 2.3017,
      "hits": [],
      "error": null
    },
    {
      "rank_vol": 67,
      "symbol": "ATH/USDT",
      "quote_volume": 0.0,
      "total_klines": 288,
      "hit_count": 0,
      "max_amplitude": 1.3363,
      "hits": [],
      "error": null
    },
    {
      "rank_vol": 68,
      "symbol": "AIXBT/USDT",
      "quote_volume": 0.0,
      "total_klines": 288,
      "hit_count": 0,
      "max_amplitude": 1.3469,
      "hits": [],
      "error": null
    },
    {
      "rank_vol": 69,
      "symbol": "TRIA/USDT",
      "quote_volume": 0.0,
      "total_klines": 288,
      "hit_count": 0,
      "max_amplitude": 4.4197,
      "hits": [],
      "error": null
    },
    {
      "rank_vol": 70,
      "symbol": "PIPPIN/USDT",
      "quote_volume": 0.0,
      "total_klines": 288,
      "hit_count": 0,
      "max_amplitude": 1.0568,
      "hits": [],
      "error": null
    },
    {
      "rank_vol": 71,
      "symbol": "ANIME/USDT",
      "quote_volume": 0.0,
      "total_klines": 288,
      "hit_count": 0,
      "max_amplitude": 1.4703,
      "hits": [],
      "error": null
    },
    {
      "rank_vol": 72,
      "symbol": "PEPE/USDT",
      "quote_volume": 0.0,
      "total_klines": 288,
      "hit_count": 0,
      "max_amplitude": 0.566,
      "hits": [],
      "error": null
    },
    {
      "rank_vol": 73,
      "symbol": "LRC/USDT",
      "quote_volume": 0.0,
      "total_klines": 288,
      "hit_count": 0,
      "max_amplitude": 5.8563,
      "hits": [],
      "error": null
    },
    {
      "rank_vol": 74,
      "symbol": "DYDX/USDT",
      "quote_volume": 0.0,
      "total_klines": 288,
      "hit_count": 0,
      "max_amplitude": 0.7651,
      "hits": [],
      "error": null
    },
    {
      "rank_vol": 75,
      "symbol": "USAR/USDT",
      "quote_volume": 0.0,
      "total_klines": 288,
      "hit_count": 0,
      "max_amplitude": 1.6418,
      "hits": [],
      "error": null
    },
    {
      "rank_vol": 76,
      "symbol": "LA/USDT",
      "quote_volume": 0.0,
      "total_klines": 288,
      "hit_count": 0,
      "max_amplitude": 1.1992,
      "hits": [],
      "error": null
    },
    {
      "rank_vol": 77,
      "symbol": "GLM/USDT",
      "quote_volume": 0.0,
      "total_klines": 288,
      "hit_count": 0,
      "max_amplitude": 0.9662,
      "hits": [],
      "error": null
    },
    {
      "rank_vol": 78,
      "symbol": "CHZ/USDT",
      "quote_volume": 0.0,
      "total_klines": 288,
      "hit_count": 0,
      "max_amplitude": 1.0353,
      "hits": [],
      "error": null
    },
    {
      "rank_vol": 79,
      "symbol": "ACH/USDT",
      "quote_volume": 0.0,
      "total_klines": 288,
      "hit_count": 0,
      "max_amplitude": 3.236,
      "hits": [],
      "error": null
    },
    {
      "rank_vol": 80,
      "symbol": "INIT/USDT",
      "quote_volume": 0.0,
      "total_klines": 288,
      "hit_count": 0,
      "max_amplitude": 3.1838,
      "hits": [],
      "error": null
    },
    {
      "rank_vol": 81,
      "symbol": "PLUME/USDT",
      "quote_volume": 0.0,
      "total_klines": 288,
      "hit_count": 0,
      "max_amplitude": 2.1123,
      "hits": [],
      "error": null
    },
    {
      "rank_vol": 82,
      "symbol": "BCH/USDT",
      "quote_volume": 0.0,
      "total_klines": 288,
      "hit_count": 0,
      "max_amplitude": 0.5082,
      "hits": [],
      "error": null
    },
    {
      "rank_vol": 83,
      "symbol": "BLUR/USDT",
      "quote_volume": 0.0,
      "total_klines": 288,
      "hit_count": 0,
      "max_amplitude": 1.2318,
      "hits": [],
      "error": null
    },
    {
      "rank_vol": 84,
      "symbol": "SENT/USDT",
      "quote_volume": 0.0,
      "total_klines": 288,
      "hit_count": 0,
      "max_amplitude": 1.0502,
      "hits": [],
      "error": null
    },
    {
      "rank_vol": 85,
      "symbol": "ALLO/USDT",
      "quote_volume": 0.0,
      "total_klines": 288,
      "hit_count": 0,
      "max_amplitude": 3.8069,
      "hits": [],
      "error": null
    },
    {
      "rank_vol": 86,
      "symbol": "XPT/USDT",
      "quote_volume": 0.0,
      "total_klines": 288,
      "hit_count": 0,
      "max_amplitude": 0.293,
      "hits": [],
      "error": null
    },
    {
      "rank_vol": 87,
      "symbol": "QQQ/USDT",
      "quote_volume": 0.0,
      "total_klines": 288,
      "hit_count": 0,
      "max_amplitude": 0.247,
      "hits": [],
      "error": null
    },
    {
      "rank_vol": 88,
      "symbol": "YGG/USDT",
      "quote_volume": 0.0,
      "total_klines": 288,
      "hit_count": 0,
      "max_amplitude": 1.1719,
      "hits": [],
      "error": null
    },
    {
      "rank_vol": 89,
      "symbol": "AAVE/USDT",
      "quote_volume": 0.0,
      "total_klines": 288,
      "hit_count": 0,
      "max_amplitude": 2.0115,
      "hits": [],
      "error": null
    },
    {
      "rank_vol": 90,
      "symbol": "METIS/USDT",
      "quote_volume": 0.0,
      "total_klines": 288,
      "hit_count": 0,
      "max_amplitude": 1.4981,
      "hits": [],
      "error": null
    },
    {
      "rank_vol": 91,
      "symbol": "ZAMA/USDT",
      "quote_volume": 0.0,
      "total_klines": 288,
      "hit_count": 0,
      "max_amplitude": 1.0862,
      "hits": [],
      "error": null
    },
    {
      "rank_vol": 92,
      "symbol": "ZK/USDT",
      "quote_volume": 0.0,
      "total_klines": 288,
      "hit_count": 0,
      "max_amplitude": 1.3434,
      "hits": [],
      "error": null
    },
    {
      "rank_vol": 93,
      "symbol": "MERL/USDT",
      "quote_volume": 0.0,
      "total_klines": 288,
      "hit_count": 0,
      "max_amplitude": 2.0161,
      "hits": [],
      "error": null
    },
    {
      "rank_vol": 94,
      "symbol": "EGLD/USDT",
      "quote_volume": 0.0,
      "total_klines": 288,
      "hit_count": 0,
      "max_amplitude": 2.4116,
      "hits": [],
      "error": null
    },
    {
      "rank_vol": 95,
      "symbol": "AVNT/USDT",
      "quote_volume": 0.0,
      "total_klines": 288,
      "hit_count": 0,
      "max_amplitude": 0.9901,
      "hits": [],
      "error": null
    },
    {
      "rank_vol": 96,
      "symbol": "HMSTR/USDT",
      "quote_volume": 0.0,
      "total_klines": 288,
      "hit_count": 0,
      "max_amplitude": 1.4373,
      "hits": [],
      "error": null
    },
    {
      "rank_vol": 97,
      "symbol": "AGLD/USDT",
      "quote_volume": 0.0,
      "total_klines": 288,
      "hit_count": 0,
      "max_amplitude": 0.5712,
      "hits": [],
      "error": null
    },
    {
      "rank_vol": 98,
      "symbol": "ONT/USDT",
      "quote_volume": 0.0,
      "total_klines": 288,
      "hit_count": 0,
      "max_amplitude": 1.7541,
      "hits": [],
      "error": null
    },
    {
      "rank_vol": 99,
      "symbol": "ALGO/USDT",
      "quote_volume": 0.0,
      "total_klines": 288,
      "hit_count": 0,
      "max_amplitude": 1.1833,
      "hits": [],
      "error": null
    },
    {
      "rank_vol": 100,
      "symbol": "ADA/USDT",
      "quote_volume": 0.0,
      "total_klines": 288,
      "hit_count": 0,
      "max_amplitude": 1.9488,
      "hits": [],
      "error": null
    }
  ]
}